{"info":{"_postman_id":"26678132-80f3-4453-8cca-110a2840d084","name":"restock","schema":"https://schema.getpostman.com/json/collection/v2.0.0/collection.json","toc":[],"description":"<html><head></head><body></body></html>","owner":"2676638","collectionId":"26678132-80f3-4453-8cca-110a2840d084","publishedId":"2sAYQUptZc","public":true,"customColor":{"top-bar":"FFFFFF","right-sidebar":"303030","highlight":"FF6C37"},"publishDate":"2025-01-09T10:02:26.000Z"},"item":[{"name":"auth","item":[{"name":"login","id":"4bea485c-fff5-4e2b-b89e-237dc095a3fc","protocolProfileBehavior":{"disableBodyPruning":true},"request":{"method":"POST","header":[],"body":{"mode":"raw","raw":"{\n    \"email\": \"habeehola18@gmail.com\",\n    \"password\": \"Password@12\"\n    // \"deviceToken\": \"\"\n}","options":{"raw":{"language":"json"}}},"url":"localhost:6005/api/auth/login","urlObject":{"port":"6005","path":["api","auth","login"],"host":["localhost"],"query":[],"variable":[]}},"response":[],"_postman_id":"4bea485c-fff5-4e2b-b89e-237dc095a3fc"},{"name":"login with google","id":"4c236e24-da4e-46d7-b784-9530d91e3759","protocolProfileBehavior":{"disableBodyPruning":true},"request":{"method":"GET","header":[],"body":{"mode":"raw","raw":"{\n    \"email\": \"habeehola18@gmail.com\",\n    \"password\": \"Password@12\"\n    // \"deviceToken\": \"\"\n}","options":{"raw":{"language":"json"}}},"url":"localhost:6005/api/auth/google/login","urlObject":{"port":"6005","path":["api","auth","google","login"],"host":["localhost"],"query":[],"variable":[]}},"response":[],"_postman_id":"4c236e24-da4e-46d7-b784-9530d91e3759"},{"name":"verify google token","id":"eccb7052-e37d-4218-8129-aa126e6d03b0","protocolProfileBehavior":{"disableBodyPruning":true},"request":{"method":"POST","header":[],"body":{"mode":"raw","raw":"{\n    \"token\": \"$2b$10$.yNVFnduIn/1uawB7c3cselVZFtbJu40NTOfC5jasSqkoN7vM0R0G\",\n    \"refById\": \"\"\n}","options":{"raw":{"language":"json"}}},"url":"https://api.restockapp.ng/api/auth/google/verify-token","urlObject":{"protocol":"https","path":["api","auth","google","verify-token"],"host":["api","restockapp","ng"],"query":[],"variable":[]}},"response":[],"_postman_id":"eccb7052-e37d-4218-8129-aa126e6d03b0"},{"name":"forgot password","id":"9e6eef47-9184-4ee2-a75c-16580bc7af95","protocolProfileBehavior":{"disableBodyPruning":true},"request":{"method":"POST","header":[],"body":{"mode":"raw","raw":"{\n    \"email\": \"abubakarolatundun3@gmail.com\"\n}","options":{"raw":{"language":"json"}}},"url":"https://api.restockapp.ng/api/auth/forgot-password","urlObject":{"protocol":"https","path":["api","auth","forgot-password"],"host":["api","restockapp","ng"],"query":[],"variable":[]}},"response":[],"_postman_id":"9e6eef47-9184-4ee2-a75c-16580bc7af95"},{"name":"verify-email","id":"32c55910-1413-42b0-b92d-b0b058f23c57","protocolProfileBehavior":{"disableBodyPruning":true},"request":{"method":"POST","header":[],"body":{"mode":"raw","raw":"{\n    \"otp\": \"977358\"\n}","options":{"raw":{"language":"json"}}},"url":"localhost:5002/api/auth/verify-email","urlObject":{"port":"5002","path":["api","auth","verify-email"],"host":["localhost"],"query":[],"variable":[]}},"response":[],"_postman_id":"32c55910-1413-42b0-b92d-b0b058f23c57"},{"name":"verify token","id":"4fff0393-aba4-4f98-8b3f-109fc65a0167","protocolProfileBehavior":{"disableBodyPruning":true},"request":{"method":"POST","header":[],"body":{"mode":"raw","raw":"{\n    \"otp\": \"846749\",\n    \"email\": \"habeehola18@gmail.com\"\n}","options":{"raw":{"language":"json"}}},"url":"localhost:5004/api/auth/verify-token","urlObject":{"port":"5004","path":["api","auth","verify-token"],"host":["localhost"],"query":[],"variable":[]}},"response":[],"_postman_id":"4fff0393-aba4-4f98-8b3f-109fc65a0167"},{"name":"register","id":"5a714f94-1bec-4240-8e3b-90aedd631597","protocolProfileBehavior":{"disableBodyPruning":true},"request":{"method":"POST","header":[{"key":"Content-Type","value":"application/json","type":"text"}],"body":{"mode":"raw","raw":"{\n    \"firstName\": \"Tiamiyyu\",\n    \"lastName\": \"AbdRahmon\",\n    \"phone\": \"08165607972\",\n    \"email\": \"tiamiyuayokunle2000+1@gmail.com\",\n    \"password\": \"Ibntiamiyu01#\",\n    \"refById\": \"\"\n}","options":{"raw":{"language":"json"}}},"url":"localhost:5004/api/auth/register","urlObject":{"port":"5004","path":["api","auth","register"],"host":["localhost"],"query":[],"variable":[]}},"response":[],"_postman_id":"5a714f94-1bec-4240-8e3b-90aedd631597"},{"name":"reset password","id":"dfbbc55c-0540-4b59-9dce-cad674a580a4","protocolProfileBehavior":{"disableBodyPruning":true},"request":{"method":"POST","header":[],"body":{"mode":"raw","raw":"{\n    \"email\": \"habeehola18@gmail.com\",\n    \"password\": \"Password@12\",\n    \"otp\": \"846749\"\n}","options":{"raw":{"language":"json"}}},"url":"localhost:5004/api/auth/reset-password","urlObject":{"port":"5004","path":["api","auth","reset-password"],"host":["localhost"],"query":[],"variable":[]}},"response":[],"_postman_id":"dfbbc55c-0540-4b59-9dce-cad674a580a4"},{"name":"resend token","id":"a667d6cb-5b8f-42a7-a4a9-7ac6dcd9329a","protocolProfileBehavior":{"disableBodyPruning":true},"request":{"method":"POST","header":[],"body":{"mode":"raw","raw":"{\n    \"email\": \"habeehola18+2@gmail.com\",\n    \"type\": \"forgot-password\" // verify-email, change-password\n}","options":{"raw":{"language":"json"}}},"url":"localhost:5002/api/auth/resend-token","urlObject":{"port":"5002","path":["api","auth","resend-token"],"host":["localhost"],"query":[],"variable":[]}},"response":[],"_postman_id":"a667d6cb-5b8f-42a7-a4a9-7ac6dcd9329a"}],"id":"98cb800b-190c-4573-aba8-7d66d6208583","_postman_id":"98cb800b-190c-4573-aba8-7d66d6208583","description":""},{"name":"admin","item":[{"name":"market","item":[{"name":"get all markets","id":"b4129eca-a1aa-4398-88cb-843f40a9a0e7","protocolProfileBehavior":{"disableBodyPruning":true},"request":{"auth":{"type":"bearer","bearer":{"basicConfig":[{"key":"token","value":"{{restock_admin_token}}"}]},"isInherited":false},"method":"GET","header":[],"url":"localhost:5007/api/admin/market","urlObject":{"port":"5007","path":["api","admin","market"],"host":["localhost"],"query":[],"variable":[]}},"response":[],"_postman_id":"b4129eca-a1aa-4398-88cb-843f40a9a0e7"},{"name":"get single market","id":"5dfd52ab-c9e1-4737-9536-8772a972d701","protocolProfileBehavior":{"disableBodyPruning":true},"request":{"auth":{"type":"bearer","bearer":{"basicConfig":[{"key":"token","value":"{{restock_admin_token}}"}]},"isInherited":false},"method":"GET","header":[],"url":"localhost:5007/api/admin/market/:id","urlObject":{"port":"5007","path":["api","admin","market",":id"],"host":["localhost"],"query":[],"variable":[{"type":"any","value":"1448cd1a-c92d-4efa-b1e4-a44c4fd515ca","key":"id"}]}},"response":[],"_postman_id":"5dfd52ab-c9e1-4737-9536-8772a972d701"},{"name":"update market status","id":"ec162aec-6ff7-42f2-a7c8-cfa76ab052ed","protocolProfileBehavior":{"disableBodyPruning":true},"request":{"method":"PATCH","header":[],"body":{"mode":"raw","raw":"{\n    \"status\": \"\"\n}","options":{"raw":{"language":"json"}}},"url":"localhost:5002/api/admin/market/:id","urlObject":{"port":"5002","path":["api","admin","market",":id"],"host":["localhost"],"query":[],"variable":[{"type":"any","value":"","key":"id"}]}},"response":[],"_postman_id":"ec162aec-6ff7-42f2-a7c8-cfa76ab052ed"},{"name":"update market","id":"232c0e78-b068-404c-bec6-0cfb12a4a2e7","protocolProfileBehavior":{"disableBodyPruning":true},"request":{"method":"PUT","header":[],"body":{"mode":"raw","raw":"{\n    \"name\": \"Oshodi\",\n    \"address\": \"Oshodi road\",\n    \"image\": \"image\",\n    \"commodityIds\": [\"\"]\n}","options":{"raw":{"language":"json"}}},"url":"localhost:5002/api/admin/market/:id","urlObject":{"port":"5002","path":["api","admin","market",":id"],"host":["localhost"],"query":[],"variable":[{"type":"any","value":"","key":"id"}]}},"response":[],"_postman_id":"232c0e78-b068-404c-bec6-0cfb12a4a2e7"},{"name":"create market","id":"d57465e5-33a5-4351-a979-a1f3075c3f44","protocolProfileBehavior":{"disableBodyPruning":true},"request":{"auth":{"type":"bearer","bearer":{"basicConfig":[{"key":"token","value":"{{restock_token}}"}]},"isInherited":false},"method":"POST","header":[],"body":{"mode":"raw","raw":"{\n    \"name\": \"Sabo\",\n    \"address\": \"359 Herbert Macaulay Wy, Yaba, Lagos 101245, Lagos\",\n    \"image\": \"https://encrypted-tbn0.gstatic.com/images?q=tbn:ANd9GcQH8ejYsGzDFWdVGAwzTRPYYijifRWhCVN7EQ&s\",\n    \"commodityIds\": [\"980e58b1-4ae6-49df-a668-49dbbc307d77\"]\n}","options":{"raw":{"language":"json"}}},"url":"localhost:5002/api/admin/market","urlObject":{"port":"5002","path":["api","admin","market"],"host":["localhost"],"query":[],"variable":[]}},"response":[],"_postman_id":"d57465e5-33a5-4351-a979-a1f3075c3f44"}],"id":"734b63ae-c58d-45b4-bfcf-6c1bbccc2251","_postman_id":"734b63ae-c58d-45b4-bfcf-6c1bbccc2251","description":""},{"name":"seller","item":[{"name":"get all sellers","id":"333cd6b3-7435-4355-a2a5-7c80e01c7851","protocolProfileBehavior":{"disableBodyPruning":true},"request":{"auth":{"type":"bearer","bearer":{"basicConfig":[{"key":"token","value":"{{restock_admin_token}}"}]},"isInherited":false},"method":"GET","header":[],"url":"localhost:6005/api/admin/seller?marketId=d445fc51-e129-454f-a0d0-5dadb22a8bac","urlObject":{"port":"6005","path":["api","admin","seller"],"host":["localhost"],"query":[{"key":"marketId","value":"d445fc51-e129-454f-a0d0-5dadb22a8bac"}],"variable":[]}},"response":[],"_postman_id":"333cd6b3-7435-4355-a2a5-7c80e01c7851"},{"name":"get single seller","id":"5d30a304-a73b-444c-955b-9414e2c1ad60","protocolProfileBehavior":{"disableBodyPruning":true},"request":{"auth":{"type":"bearer","bearer":{"basicConfig":[{"key":"token","value":"{{restock_admin_token}}"}]},"isInherited":false},"method":"GET","header":[],"url":"localhost:5007/api/admin/seller/b6704d59-95e7-4b75-a543-6290eec3bdb5","urlObject":{"port":"5007","path":["api","admin","seller","b6704d59-95e7-4b75-a543-6290eec3bdb5"],"host":["localhost"],"query":[],"variable":[]}},"response":[],"_postman_id":"5d30a304-a73b-444c-955b-9414e2c1ad60"},{"name":"update seller status","id":"04081b8c-f60b-4dae-ba10-684e487f27dc","protocolProfileBehavior":{"disableBodyPruning":true},"request":{"method":"PATCH","header":[],"body":{"mode":"raw","raw":"{\n    \"status\": \"\"\n}","options":{"raw":{"language":"json"}}},"url":"localhost:5002/api/admin/seller/:id","urlObject":{"port":"5002","path":["api","admin","seller",":id"],"host":["localhost"],"query":[],"variable":[{"type":"any","value":"","key":"id"}]}},"response":[],"_postman_id":"04081b8c-f60b-4dae-ba10-684e487f27dc"},{"name":"update seller","id":"fc7c73c0-00f6-4ea8-9031-ba644c75e859","protocolProfileBehavior":{"disableBodyPruning":true},"request":{"method":"PUT","header":[],"body":{"mode":"raw","raw":"{\n    \"businessName\": \"Iya Mero\",\n    \"profileImage\": \"https://encrypted-tbn0.gstatic.com/images?q=tbn:ANd9GcQH8ejYsGzDFWdVGAwzTRPYYijifRWhCVN7EQ&s\",\n    \"categoryId\": \"4b34a675-0f2f-4ab0-ada7-90eeb4e4ce24\",\n    \"gender\": \"Female\",\n    \"fullname\": \"Adijat Olapade\",\n    \"primaryPhone\": \"08012345678\",\n    \"marketId\": \"d445fc51-e129-454f-a0d0-5dadb22a8bac\",\n    \"commodities\": []\n}","options":{"raw":{"language":"json"}}},"url":"localhost:5002/api/admin/seller/:id","urlObject":{"port":"5002","path":["api","admin","seller",":id"],"host":["localhost"],"query":[],"variable":[{"type":"any","value":"","key":"id"}]}},"response":[],"_postman_id":"fc7c73c0-00f6-4ea8-9031-ba644c75e859"},{"name":"create seller","id":"d52a4db7-1f28-45bc-a9e6-866fd8894a35","protocolProfileBehavior":{"disableBodyPruning":true},"request":{"auth":{"type":"bearer","bearer":{"basicConfig":[{"key":"token","value":"{{restock_token}}"}]},"isInherited":false},"method":"POST","header":[],"body":{"mode":"raw","raw":"{\n    \"businessName\": \"Iya Mero\",\n    \"profileImage\": \"https://encrypted-tbn0.gstatic.com/images?q=tbn:ANd9GcQH8ejYsGzDFWdVGAwzTRPYYijifRWhCVN7EQ&s\",\n    \"categoryId\": \"4b34a675-0f2f-4ab0-ada7-90eeb4e4ce24\",\n    \"gender\": \"Female\",\n    \"fullname\": \"Adijat Olapade\",\n    \"primaryPhone\": \"08012345678\",\n    \"marketId\": \"d445fc51-e129-454f-a0d0-5dadb22a8bac\",\n    \"commodities\": []\n}","options":{"raw":{"language":"json"}}},"url":"localhost:5002/api/admin/seller","urlObject":{"port":"5002","path":["api","admin","seller"],"host":["localhost"],"query":[],"variable":[]}},"response":[],"_postman_id":"d52a4db7-1f28-45bc-a9e6-866fd8894a35"}],"id":"4d915b09-3a28-43e5-9c62-e02861f2f03d","_postman_id":"4d915b09-3a28-43e5-9c62-e02861f2f03d","description":""},{"name":"product","item":[{"name":"get products","id":"aefcf426-575c-4f8b-86de-c5caa72c23d0","protocolProfileBehavior":{"disableBodyPruning":true},"request":{"auth":{"type":"bearer","bearer":{"basicConfig":[{"key":"token","value":"{{restock_token}}"}]},"isInherited":false},"method":"GET","header":[],"url":"localhost:5002/api/admin/product","urlObject":{"port":"5002","path":["api","admin","product"],"host":["localhost"],"query":[],"variable":[]}},"response":[],"_postman_id":"aefcf426-575c-4f8b-86de-c5caa72c23d0"},{"name":"get market prices","id":"0b86a890-0828-4447-87d8-68b6372e1963","protocolProfileBehavior":{"disableBodyPruning":true},"request":{"auth":{"type":"bearer","bearer":{"basicConfig":[{"key":"token","value":"{{restock_admin_token}}"}]},"isInherited":false},"method":"GET","header":[],"url":"localhost:5007/api/admin/product/market-price?sellerId=decf8b78-794f-4f88-acd1-f6d47ec583ee","urlObject":{"port":"5007","path":["api","admin","product","market-price"],"host":["localhost"],"query":[{"key":"sellerId","value":"decf8b78-794f-4f88-acd1-f6d47ec583ee"}],"variable":[]}},"response":[],"_postman_id":"0b86a890-0828-4447-87d8-68b6372e1963"},{"name":"create market price","id":"c610a2e4-17a1-47d3-9a0a-196980a60cc3","protocolProfileBehavior":{"disableBodyPruning":true},"request":{"auth":{"type":"bearer","bearer":{"basicConfig":[{"key":"token","value":"{{restock_token}}"}]},"isInherited":false},"method":"POST","header":[],"body":{"mode":"raw","raw":"{\n      \"commodityId\": \"7c484676-8a7e-4d5b-8ae1-33c31f6ef928\",\n\"marketId\": \"d63baab7-965a-4587-8133-494352bb532a\",\n\"measurements\": [{\"id\": \"675e6b35-2f20-4f29-b55a-e2f5c4b5c696\", \"price\": \"61000\"}],\n\"sellerId\": \"e1c9f28f-97af-47b7-8edc-3cc4a67534e\"\n}","options":{"raw":{"language":"json"}}},"url":"localhost:6005/api/admin/product/market-price","urlObject":{"port":"6005","path":["api","admin","product","market-price"],"host":["localhost"],"query":[],"variable":[]}},"response":[],"_postman_id":"c610a2e4-17a1-47d3-9a0a-196980a60cc3"},{"name":"update market price","id":"47a66372-b2d5-4d53-a6d5-54565536033b","protocolProfileBehavior":{"disableBodyPruning":true},"request":{"method":"PUT","header":[],"body":{"mode":"raw","raw":"{\n      \"sellerId\": \"\",\n      \"marketId\": \"\",\n      \"commodityId\": \"\",\n      \"price\": \"\"\n}","options":{"raw":{"language":"json"}}},"url":"localhost:5002/api/admin/product/market-price/:id","urlObject":{"port":"5002","path":["api","admin","product","market-price",":id"],"host":["localhost"],"query":[],"variable":[{"type":"any","value":"","key":"id"}]}},"response":[],"_postman_id":"47a66372-b2d5-4d53-a6d5-54565536033b"},{"name":"create product","id":"8b012e20-5a01-4fa3-9d5f-012b49637763","protocolProfileBehavior":{"disableBodyPruning":true},"request":{"auth":{"type":"bearer","bearer":{"basicConfig":[{"key":"token","value":"{{restock_token}}"}]},"isInherited":false},"method":"POST","header":[],"body":{"mode":"raw","raw":"{\n    \"name\": \"Black pepper\",\n    \"imageUrl\": \"https://images-prod.healthline.com/hlcmsresource/images/AN_images/tomatoes-1296x728-feature.jpg\",\n    \"categoryId\": \"4b34a675-0f2f-4ab0-ada7-90eeb4e4ce24\",\n    \"measurements\": [\"\"]\n}","options":{"raw":{"language":"json"}}},"url":"localhost:5002/api/admin/product","urlObject":{"port":"5002","path":["api","admin","product"],"host":["localhost"],"query":[],"variable":[]}},"response":[],"_postman_id":"8b012e20-5a01-4fa3-9d5f-012b49637763"},{"name":"update product","id":"51b7c1b6-4c17-48f7-97dc-932df8195c2c","protocolProfileBehavior":{"disableBodyPruning":true},"request":{"auth":{"type":"bearer","bearer":{"basicConfig":[{"key":"token","value":"{{restock_token}}"}]},"isInherited":false},"method":"PUT","header":[],"body":{"mode":"raw","raw":"{\n    \"categoryId\": \"e005b881-8c32-4d03-9f2d-e90f494ae1fc\",\n\"imageUrl\": \"https://res.cloudinary.com/dae0rudcd/image/upload/v1740327839/jkqxhakwkg19fvlhlidi.png\",\n\"measurements\": [\"bb5976e3-6581-4a1d-b4d5-16d2b1372a9f\", \"1c9f9dc6-c36a-438c-b891-176ec22b581c\"],\n\"name\": \"Chickens\"\n}","options":{"raw":{"language":"json"}}},"url":"localhost:5002/api/admin/product/:id","urlObject":{"port":"5002","path":["api","admin","product",":id"],"host":["localhost"],"query":[],"variable":[{"type":"any","value":"99f2ccb1-7804-4c05-8cc3-7a90514e238f","key":"id"}]}},"response":[],"_postman_id":"51b7c1b6-4c17-48f7-97dc-932df8195c2c"},{"name":"update product status","id":"fc37ce88-fc99-4a37-8e2c-733eab384779","protocolProfileBehavior":{"disableBodyPruning":true},"request":{"method":"PATCH","header":[],"body":{"mode":"raw","raw":"{\n    \"status\": \"\"\n}","options":{"raw":{"language":"json"}}},"url":"localhost:5002/api/admin/product/:id","urlObject":{"port":"5002","path":["api","admin","product",":id"],"host":["localhost"],"query":[],"variable":[{"type":"any","value":"","key":"id"}]}},"response":[],"_postman_id":"fc37ce88-fc99-4a37-8e2c-733eab384779"}],"id":"f9bdf406-6964-4eff-84d5-684dde44c227","_postman_id":"f9bdf406-6964-4eff-84d5-684dde44c227","description":""},{"name":"order","item":[{"name":"get orders","id":"9223b0c0-b7b3-4d40-8451-fb8ab036eb76","protocolProfileBehavior":{"disableBodyPruning":true},"request":{"method":"GET","header":[],"url":"localhost:5002/api/admin/order","urlObject":{"port":"5002","path":["api","admin","order"],"host":["localhost"],"query":[],"variable":[]}},"response":[],"_postman_id":"9223b0c0-b7b3-4d40-8451-fb8ab036eb76"},{"name":"update order status","id":"bb0a1354-3ffe-4fc5-ae6c-133697e62616","protocolProfileBehavior":{"disableBodyPruning":true},"request":{"method":"PATCH","header":[],"body":{"mode":"raw","raw":"{\n    \"status\": \"\",\n    \"cancelReason\": \"\"\n}","options":{"raw":{"language":"json"}}},"url":"localhost:5002/api/admin/order/:id","urlObject":{"port":"5002","path":["api","admin","order",":id"],"host":["localhost"],"query":[],"variable":[{"type":"any","value":"","key":"id"}]}},"response":[],"_postman_id":"bb0a1354-3ffe-4fc5-ae6c-133697e62616"}],"id":"f760bc58-b1fe-42db-9b3e-6d16779e847a","_postman_id":"f760bc58-b1fe-42db-9b3e-6d16779e847a","description":""},{"name":"tag","item":[{"name":"get tags","id":"4b88a5d4-f111-410c-8a6f-61e3d8a0066c","protocolProfileBehavior":{"disableBodyPruning":true},"request":{"auth":{"type":"bearer","bearer":{"basicConfig":[{"key":"token","value":"{{restock_token}}"}]},"isInherited":false},"method":"GET","header":[],"url":"localhost:5002/api/admin/tag","urlObject":{"port":"5002","path":["api","admin","tag"],"host":["localhost"],"query":[],"variable":[]}},"response":[],"_postman_id":"4b88a5d4-f111-410c-8a6f-61e3d8a0066c"},{"name":"create tag","id":"47d9f590-031b-4fc6-8d70-67f6bcea48ab","protocolProfileBehavior":{"disableBodyPruning":true},"request":{"auth":{"type":"bearer","bearer":{"basicConfig":[{"key":"token","value":"{{restock_token}}"}]},"isInherited":false},"method":"POST","header":[],"body":{"mode":"raw","raw":"{\n    \"name\": \"Handpicked for you\",\n    \"description\": \"specially pick just for you\",\n    \"type\": \"Products\" // valid type \"Products\", \"Markets\"\n}","options":{"raw":{"language":"json"}}},"url":"localhost:5002/api/admin/tag","urlObject":{"port":"5002","path":["api","admin","tag"],"host":["localhost"],"query":[],"variable":[]}},"response":[],"_postman_id":"47d9f590-031b-4fc6-8d70-67f6bcea48ab"},{"name":"tag product or market","id":"ac817320-06ef-4fae-b348-a8fe5c52a85a","protocolProfileBehavior":{"disableBodyPruning":true},"request":{"auth":{"type":"bearer","bearer":{"basicConfig":[{"key":"token","value":"{{restock_token}}"}]},"isInherited":false},"method":"POST","header":[],"body":{"mode":"raw","raw":"{\n    \"productIds\": [{\"marketId\": \"d445fc51-e129-454f-a0d0-5dadb22a8bac\", \"commodityId\": \"980e58b1-4ae6-49df-a668-49dbbc307d77\"},\n    {\"marketId\": \"d445fc51-e129-454f-a0d0-5dadb22a8bac\", \"commodityId\": \"04c94f9c-80a7-4c7f-9f62-34d475526afe\"}], // optional\n    // \"marketIds\": [\"d445fc51-e129-454f-a0d0-5dadb22a8bac\"], // optional\n    // \"tagId\": \"6d7f98c7-d9b1-4046-87b9-7fe0cb45b7dd\"\n    // \"marketIds\": [\"d63baab7-965a-4587-8133-494352bb532a\", \"d445fc51-e129-454f-a0d0-5dadb22a8bac\"],\n\"tagId\": \"6411c7f6-2fb9-48e3-997b-4a079478786d\"\n}","options":{"raw":{"language":"json"}}},"url":"localhost:5002/api/admin/tag/tagProductOrMarket","urlObject":{"port":"5002","path":["api","admin","tag","tagProductOrMarket"],"host":["localhost"],"query":[],"variable":[]}},"response":[],"_postman_id":"ac817320-06ef-4fae-b348-a8fe5c52a85a"},{"name":"update tag","id":"c04f28a0-75a7-4de5-b62d-8f3c3a0ac103","protocolProfileBehavior":{"disableBodyPruning":true},"request":{"method":"PUT","header":[],"body":{"mode":"raw","raw":"{\n    \"name\": \"\",\n    \"description\": \"\"\n}","options":{"raw":{"language":"json"}}},"url":"localhost:5002/api/admin/tag/:id","urlObject":{"port":"5002","path":["api","admin","tag",":id"],"host":["localhost"],"query":[],"variable":[{"type":"any","value":"","key":"id"}]}},"response":[],"_postman_id":"c04f28a0-75a7-4de5-b62d-8f3c3a0ac103"},{"name":"update tag status","id":"61340e7b-374d-4c58-ba1f-58aaa7c72873","protocolProfileBehavior":{"disableBodyPruning":true},"request":{"method":"PATCH","header":[],"body":{"mode":"raw","raw":"{\n    \"status\": \"\"\n}","options":{"raw":{"language":"json"}}},"url":"localhost:5002/api/admin/tag/:id","urlObject":{"port":"5002","path":["api","admin","tag",":id"],"host":["localhost"],"query":[],"variable":[{"type":"any","value":"","key":"id"}]}},"response":[],"_postman_id":"61340e7b-374d-4c58-ba1f-58aaa7c72873"}],"id":"9aa44435-7700-49e4-b653-6f6268a6869d","_postman_id":"9aa44435-7700-49e4-b653-6f6268a6869d","description":""},{"name":"wishlist","item":[{"name":"get wishlists","id":"d1dadc1c-a3ea-4737-9e9f-142fab465613","protocolProfileBehavior":{"disableBodyPruning":true},"request":{"method":"GET","header":[],"url":"localhost:5002/api/admin/wishlist","urlObject":{"port":"5002","path":["api","admin","wishlist"],"host":["localhost"],"query":[],"variable":[]}},"response":[],"_postman_id":"d1dadc1c-a3ea-4737-9e9f-142fab465613"}],"id":"f064b237-e38c-4ea4-8bb4-c561be685b40","_postman_id":"f064b237-e38c-4ea4-8bb4-c561be685b40","description":""},{"name":"category","item":[{"name":"get all categories","id":"4e4d5a9f-700a-405b-9803-c8a832eadff8","protocolProfileBehavior":{"disableBodyPruning":true},"request":{"auth":{"type":"bearer","bearer":{"basicConfig":[{"key":"token","value":"{{restock_token}}"}]},"isInherited":false},"method":"GET","header":[],"url":"localhost:5007/api/admin/category","urlObject":{"port":"5007","path":["api","admin","category"],"host":["localhost"],"query":[],"variable":[]}},"response":[],"_postman_id":"4e4d5a9f-700a-405b-9803-c8a832eadff8"},{"name":"create category","id":"5c029f62-e18b-46d1-b361-9d82c86f0226","protocolProfileBehavior":{"disableBodyPruning":true},"request":{"auth":{"type":"bearer","bearer":{"basicConfig":[{"key":"token","value":"{{restock_token}}"}]},"isInherited":false},"method":"POST","header":[],"body":{"mode":"raw","raw":"{\n    \"name\": \"Pepper\",\n    \"image\": \"\"\n}","options":{"raw":{"language":"json"}}},"url":"localhost:5002/api/admin/category","urlObject":{"port":"5002","path":["api","admin","category"],"host":["localhost"],"query":[],"variable":[]}},"response":[],"_postman_id":"5c029f62-e18b-46d1-b361-9d82c86f0226"}],"id":"834928cb-f08b-4cec-a162-fdce9006c6c5","_postman_id":"834928cb-f08b-4cec-a162-fdce9006c6c5","description":""},{"name":"banner","item":[{"name":"get all banners","id":"6a9be6d4-0856-4236-8e1d-945dc8b61bbe","protocolProfileBehavior":{"disableBodyPruning":true},"request":{"auth":{"type":"bearer","bearer":{"basicConfig":[{"key":"token","value":"{{restock_token}}"}]},"isInherited":false},"method":"GET","header":[],"url":"localhost:5002/api/admin/banner","urlObject":{"port":"5002","path":["api","admin","banner"],"host":["localhost"],"query":[],"variable":[]}},"response":[],"_postman_id":"6a9be6d4-0856-4236-8e1d-945dc8b61bbe"},{"name":"create banner","id":"b39880d0-e475-4a6d-8e62-187c8b463fc0","protocolProfileBehavior":{"disableBodyPruning":true},"request":{"auth":{"type":"bearer","bearer":{"basicConfig":[{"key":"token","value":"{{restock_token}}"}]},"isInherited":false},"method":"POST","header":[],"body":{"mode":"raw","raw":"{\n    \"description\": \"Pepper\",\n    \"imageUrl\": \"\",\n    \"link\": \"\"\n}","options":{"raw":{"language":"json"}}},"url":"localhost:5002/api/admin/banner","urlObject":{"port":"5002","path":["api","admin","banner"],"host":["localhost"],"query":[],"variable":[]}},"response":[],"_postman_id":"b39880d0-e475-4a6d-8e62-187c8b463fc0"},{"name":"delete banner","id":"538c7be1-4e8e-4454-90af-4d59a7b7b849","protocolProfileBehavior":{"disableBodyPruning":true},"request":{"auth":{"type":"bearer","bearer":{"basicConfig":[{"key":"token","value":"{{restock_token}}"}]},"isInherited":false},"method":"DELETE","header":[],"body":{"mode":"raw","raw":"","options":{"raw":{"language":"json"}}},"url":"localhost:5002/api/admin/banner/:id","urlObject":{"port":"5002","path":["api","admin","banner",":id"],"host":["localhost"],"query":[],"variable":[{"type":"any","value":"","key":"id"}]}},"response":[],"_postman_id":"538c7be1-4e8e-4454-90af-4d59a7b7b849"},{"name":"update banner","id":"7131d432-c065-419f-9e03-e9170c37be2c","protocolProfileBehavior":{"disableBodyPruning":true},"request":{"auth":{"type":"bearer","bearer":{"basicConfig":[{"key":"token","value":"{{restock_token}}"}]},"isInherited":false},"method":"PUT","header":[],"body":{"mode":"raw","raw":"{\n    \"description\": \"Pepper\",\n    \"imageUrl\": \"\",\n    \"link\": \"\"\n}","options":{"raw":{"language":"json"}}},"url":"localhost:5002/api/admin/banner/:id","urlObject":{"port":"5002","path":["api","admin","banner",":id"],"host":["localhost"],"query":[],"variable":[{"type":"any","value":"","key":"id"}]}},"response":[],"_postman_id":"7131d432-c065-419f-9e03-e9170c37be2c"}],"id":"fcc72db9-5328-4424-b0bf-bce18477e6e4","_postman_id":"fcc72db9-5328-4424-b0bf-bce18477e6e4","description":""},{"name":"measurements","item":[{"name":"get all measurements","id":"9c01a7c7-2035-4244-bd64-b96298332b83","protocolProfileBehavior":{"disableBodyPruning":true},"request":{"auth":{"type":"bearer","bearer":{"basicConfig":[{"key":"token","value":"{{restock_token}}"}]},"isInherited":false},"method":"GET","header":[],"url":"localhost:5002/api/admin/measurement","urlObject":{"port":"5002","path":["api","admin","measurement"],"host":["localhost"],"query":[],"variable":[]}},"response":[],"_postman_id":"9c01a7c7-2035-4244-bd64-b96298332b83"},{"name":"create measurement","id":"8f934343-6f33-436a-a6f5-e730c4c13bc5","protocolProfileBehavior":{"disableBodyPruning":true},"request":{"auth":{"type":"bearer","bearer":{"basicConfig":[{"key":"token","value":"{{restock_token}}"}]},"isInherited":false},"method":"POST","header":[],"body":{"mode":"raw","raw":"{\n    \"name\": \"Kg\"\n}","options":{"raw":{"language":"json"}}},"url":"localhost:5002/api/admin/measurement","urlObject":{"port":"5002","path":["api","admin","measurement"],"host":["localhost"],"query":[],"variable":[]}},"response":[],"_postman_id":"8f934343-6f33-436a-a6f5-e730c4c13bc5"},{"name":"delete measurement","id":"95ec325b-f5bc-4903-8cc7-c3a961aacc92","protocolProfileBehavior":{"disableBodyPruning":true},"request":{"auth":{"type":"bearer","bearer":{"basicConfig":[{"key":"token","value":"{{restock_token}}"}]},"isInherited":false},"method":"DELETE","header":[],"body":{"mode":"raw","raw":"","options":{"raw":{"language":"json"}}},"url":"localhost:5002/api/admin/measurement/:id","urlObject":{"port":"5002","path":["api","admin","measurement",":id"],"host":["localhost"],"query":[],"variable":[{"type":"any","value":"","key":"id"}]}},"response":[],"_postman_id":"95ec325b-f5bc-4903-8cc7-c3a961aacc92"},{"name":"update measurement","id":"82e2d7cc-c9c1-481c-adcc-fe2d350a25c4","protocolProfileBehavior":{"disableBodyPruning":true},"request":{"auth":{"type":"bearer","bearer":{"basicConfig":[{"key":"token","value":"{{restock_token}}"}]},"isInherited":false},"method":"PUT","header":[],"body":{"mode":"raw","raw":"{\n    \"name\": \"Liter\"\n}","options":{"raw":{"language":"json"}}},"url":"localhost:5002/api/admin/measurement/:id","urlObject":{"port":"5002","path":["api","admin","measurement",":id"],"host":["localhost"],"query":[],"variable":[{"type":"any","value":"","key":"id"}]}},"response":[],"_postman_id":"82e2d7cc-c9c1-481c-adcc-fe2d350a25c4"}],"id":"bf369ee1-6511-43c3-867f-ae507f3d3bf9","_postman_id":"bf369ee1-6511-43c3-867f-ae507f3d3bf9","description":""},{"name":"settings","item":[{"name":"get settings","id":"0f79cd39-d751-4f45-84a6-e495fd1a09d2","protocolProfileBehavior":{"disableBodyPruning":true},"request":{"auth":{"type":"bearer","bearer":{"basicConfig":[{"key":"token","value":"{{restock_token}}"}]},"isInherited":false},"method":"GET","header":[],"url":"localhost:5002/api/admin/setting","urlObject":{"port":"5002","path":["api","admin","setting"],"host":["localhost"],"query":[],"variable":[]}},"response":[],"_postman_id":"0f79cd39-d751-4f45-84a6-e495fd1a09d2"},{"name":"create setting","id":"349d7cdb-d079-4abc-9fdb-f121f3731d42","protocolProfileBehavior":{"disableBodyPruning":true},"request":{"auth":{"type":"bearer","bearer":{"basicConfig":[{"key":"token","value":"{{restock_token}}"}]},"isInherited":false},"method":"POST","header":[],"body":{"mode":"raw","raw":"{\n    \"name\": \"serviceCharge\",\n    \"config\": {\n        \"charges\": 10,\n        \"capPrice\": 200000\n    }\n}","options":{"raw":{"language":"json"}}},"url":"localhost:5002/api/admin/setting","urlObject":{"port":"5002","path":["api","admin","setting"],"host":["localhost"],"query":[],"variable":[]}},"response":[],"_postman_id":"349d7cdb-d079-4abc-9fdb-f121f3731d42"},{"name":"delete setting","id":"de274120-577f-4ad1-86a9-739293ebf0f0","protocolProfileBehavior":{"disableBodyPruning":true},"request":{"auth":{"type":"bearer","bearer":{"basicConfig":[{"key":"token","value":"{{restock_token}}"}]},"isInherited":false},"method":"DELETE","header":[],"body":{"mode":"raw","raw":"{\n    \"status\": true\n}","options":{"raw":{"language":"json"}}},"url":"localhost:5002/api/admin/setting/:id","urlObject":{"port":"5002","path":["api","admin","setting",":id"],"host":["localhost"],"query":[],"variable":[{"type":"any","value":"","key":"id"}]}},"response":[],"_postman_id":"de274120-577f-4ad1-86a9-739293ebf0f0"},{"name":"update setting","id":"eaad6f36-709e-45ea-9e1e-3e9b6f676bae","protocolProfileBehavior":{"disableBodyPruning":true},"request":{"auth":{"type":"bearer","bearer":{"basicConfig":[{"key":"token","value":"{{restock_token}}"}]},"isInherited":false},"method":"PUT","header":[],"body":{"mode":"raw","raw":"{\n    \"name\": \"Liter\",\n    \"config\": {\n        \"charges\": 10,\n        \"capPrice\": 200000\n    }\n}","options":{"raw":{"language":"json"}}},"url":"localhost:5002/api/admin/setting/:id","urlObject":{"port":"5002","path":["api","admin","setting",":id"],"host":["localhost"],"query":[],"variable":[{"type":"any","value":"","key":"id"}]}},"response":[],"_postman_id":"eaad6f36-709e-45ea-9e1e-3e9b6f676bae"}],"id":"40e42d4d-070c-4da8-b826-97cb1ec11f30","_postman_id":"40e42d4d-070c-4da8-b826-97cb1ec11f30","description":""},{"name":"role","item":[{"name":"get all roles","id":"3c151c02-2f40-4bc0-858b-56c054657e28","protocolProfileBehavior":{"disableBodyPruning":true},"request":{"auth":{"type":"bearer","bearer":{"basicConfig":[{"key":"token","value":"{{restock_admin_token}}"}]},"isInherited":false},"method":"GET","header":[],"url":"localhost:5007/api/admin/role","urlObject":{"port":"5007","path":["api","admin","role"],"host":["localhost"],"query":[],"variable":[]}},"response":[],"_postman_id":"3c151c02-2f40-4bc0-858b-56c054657e28"},{"name":"create role","id":"e0e9eec0-968a-4919-ba2f-69ee7d482e5d","protocolProfileBehavior":{"disableBodyPruning":true},"request":{"auth":{"type":"bearer","bearer":{"basicConfig":[{"key":"token","value":"{{restock_token}}"}]},"isInherited":false},"method":"POST","header":[],"body":{"mode":"raw","raw":"{\n    \"name\": \"Agent\"\n}","options":{"raw":{"language":"json"}}},"url":"http://localhost:5007/api/admin/role","urlObject":{"protocol":"http","port":"5007","path":["api","admin","role"],"host":["localhost"],"query":[],"variable":[]}},"response":[],"_postman_id":"e0e9eec0-968a-4919-ba2f-69ee7d482e5d"}],"id":"303d95a1-2daf-4a92-8351-2200d07b1c77","_postman_id":"303d95a1-2daf-4a92-8351-2200d07b1c77","description":""},{"name":"auth","item":[{"name":"login admin","id":"92ff7aec-5580-45a5-9d00-e89962d6be4c","protocolProfileBehavior":{"disableBodyPruning":true},"request":{"method":"POST","header":[],"body":{"mode":"raw","raw":"{\n    \"email\": \"habeehola18@gmail.com\",\n    \"password\": \"Password@123\"\n}","options":{"raw":{"language":"json"}}},"url":"localhost:5007/api/auth/admin/login","urlObject":{"port":"5007","path":["api","auth","admin","login"],"host":["localhost"],"query":[],"variable":[]}},"response":[],"_postman_id":"92ff7aec-5580-45a5-9d00-e89962d6be4c"},{"name":"create admin","id":"8ea3109c-9f59-4099-9fc0-b93c786274bc","protocolProfileBehavior":{"disableBodyPruning":true},"request":{"auth":{"type":"bearer","bearer":{"basicConfig":[{"key":"token","value":"{{restock_admin_token}}"}]},"isInherited":false},"method":"POST","header":[],"body":{"mode":"raw","raw":"{\n    \"firstName\": \"Rasheed\",\n    \"lastName\": \"Dada\",\n    \"phone\": \"08165607972\",\n    \"email\": \"habeehola18@gmail.com\",\n    \"password\": \"Password@123\",\n    \"roleId\": \"630f116a-5e2f-4dc5-8021-e69104b93cfd\"\n}","options":{"raw":{"language":"json"}}},"url":"http://localhost:5007/api/admin/create-user","urlObject":{"protocol":"http","port":"5007","path":["api","admin","create-user"],"host":["localhost"],"query":[],"variable":[]}},"response":[],"_postman_id":"8ea3109c-9f59-4099-9fc0-b93c786274bc"}],"id":"920fafb9-aec1-432c-8c4c-82e70fc8b24b","_postman_id":"920fafb9-aec1-432c-8c4c-82e70fc8b24b","description":""},{"name":"users","item":[{"name":"get users","id":"2139d835-b55f-49bf-85ba-dccd3a6c3ae6","protocolProfileBehavior":{"disableBodyPruning":true},"request":{"auth":{"type":"bearer","bearer":{"basicConfig":[{"key":"token","value":"{{restock_token}}"}]},"isInherited":false},"method":"GET","header":[],"url":"localhost:5002/api/admin/user","urlObject":{"port":"5002","path":["api","admin","user"],"host":["localhost"],"query":[],"variable":[]}},"response":[],"_postman_id":"2139d835-b55f-49bf-85ba-dccd3a6c3ae6"},{"name":"get admins","id":"898e06be-f65e-4a8a-a57d-3d89e9ac837b","protocolProfileBehavior":{"disableBodyPruning":true},"request":{"auth":{"type":"bearer","bearer":{"basicConfig":[{"key":"token","value":"{{restock_token}}"}]},"isInherited":false},"method":"GET","header":[],"url":"localhost:5002/api/admin/","urlObject":{"port":"5002","path":["api","admin",""],"host":["localhost"],"query":[],"variable":[]}},"response":[],"_postman_id":"898e06be-f65e-4a8a-a57d-3d89e9ac837b"},{"name":"shopper accept or reject order","id":"360d2669-11d0-44cb-841e-785f2d340f9b","protocolProfileBehavior":{"disableBodyPruning":true},"request":{"auth":{"type":"bearer","bearer":{"basicConfig":[{"key":"token","value":"{{restock_token}}"}]},"isInherited":false},"method":"PUT","header":[],"body":{"mode":"raw","raw":"{\n    \"status\": \"accept\" // reject\n}","options":{"raw":{"language":"json"}}},"url":"localhost:5002/api/admin/user/shopper/:id","urlObject":{"port":"5002","path":["api","admin","user","shopper",":id"],"host":["localhost"],"query":[],"variable":[{"type":"any","value":"","key":"id"}]}},"response":[],"_postman_id":"360d2669-11d0-44cb-841e-785f2d340f9b"},{"name":"get waitlist users","id":"6a0b47c3-b800-46d7-8496-8c918a46bb03","protocolProfileBehavior":{"disableBodyPruning":true},"request":{"auth":{"type":"bearer","bearer":{"basicConfig":[{"key":"token","value":"{{restock_token}}"}]},"isInherited":false},"method":"GET","header":[],"url":"localhost:5002/api/admin/user/waitlist","urlObject":{"port":"5002","path":["api","admin","user","waitlist"],"host":["localhost"],"query":[],"variable":[]}},"response":[],"_postman_id":"6a0b47c3-b800-46d7-8496-8c918a46bb03"}],"id":"af983845-aaf8-4923-ab61-22d968688d82","_postman_id":"af983845-aaf8-4923-ab61-22d968688d82","description":""},{"name":"coupon","item":[{"name":"create coupon","id":"9de9bada-4b5e-4f76-833a-e51aee9aa1e0","protocolProfileBehavior":{"disableBodyPruning":true},"request":{"auth":{"type":"bearer","bearer":{"basicConfig":[{"key":"token","value":"{{restock_admin_token}}"}]},"isInherited":false},"method":"POST","header":[],"body":{"mode":"raw","raw":"{\n    \"name\":            \"Welcome promo\",\n    \"description\":     \"A promo code for new user \",\n    \"type\":            \"Percentage\",\n    \"usageDuration\":   1,\n    \"usageCondition\":  \"Everyone\",\n    \"code\":            \"PROMO\",\n    \"value\":           10,\n    \"minimumPurchase\": 2000,\n    \"maximumDiscount\": 5000,\n    \"startDate\":       \"2025-07-30T12:02:47.111Z\",\n    \"endDate\":         \"2025-08-30T12:02:47.111Z\"\n}","options":{"raw":{"language":"json"}}},"url":"localhost:5007/api/admin/coupon","urlObject":{"port":"5007","path":["api","admin","coupon"],"host":["localhost"],"query":[],"variable":[]}},"response":[],"_postman_id":"9de9bada-4b5e-4f76-833a-e51aee9aa1e0"},{"name":"update coupon","id":"9a8dd2e4-60bf-457e-8faf-ca0dce270d98","protocolProfileBehavior":{"disableBodyPruning":true},"request":{"auth":{"type":"bearer","bearer":{"basicConfig":[{"key":"token","value":"{{restock_admin_token}}"}]},"isInherited":false},"method":"PUT","header":[],"body":{"mode":"raw","raw":"{\n    // \"name\":            \"\",\n    \"description\":     \"A promo for all new comers\",\n    \"type\":            \"Percentage\",\n    \"usageDuration\":   4\n}","options":{"raw":{"language":"json"}}},"url":"localhost:5007/api/admin/coupon/:id","urlObject":{"port":"5007","path":["api","admin","coupon",":id"],"host":["localhost"],"query":[],"variable":[{"type":"any","value":"bd90c7af-fa5b-4093-9030-e426b8295a37","key":"id"}]}},"response":[],"_postman_id":"9a8dd2e4-60bf-457e-8faf-ca0dce270d98"},{"name":"get coupons","id":"37a98cb6-fa03-49eb-ad94-f386ded0fe96","protocolProfileBehavior":{"disableBodyPruning":true},"request":{"auth":{"type":"bearer","bearer":{"basicConfig":[{"key":"token","value":"{{restock_admin_token}}"}]},"isInherited":false},"method":"GET","header":[],"body":{"mode":"raw","raw":"{\n    \"name\":            \"\",\n    \"description\":     \"\",\n    \"type\":            \"PERCENT\",\n    \"usageDuration\":   2,\n    \"usageCondition\":  \"Everyone\",\n    \"code\":            \"PROMO\",\n    \"value\":           10,\n    \"minimumPurchase\": 2500,\n    \"maximumDiscount\": 1000,\n    \"startDate\":       \"\",\n    \"endDate\":         \"\"\n}","options":{"raw":{"language":"json"}}},"url":"localhost:5007/api/admin/coupon","urlObject":{"port":"5007","path":["api","admin","coupon"],"host":["localhost"],"query":[],"variable":[]}},"response":[],"_postman_id":"37a98cb6-fa03-49eb-ad94-f386ded0fe96"}],"id":"066cdc77-7602-4155-86b5-309283d01644","_postman_id":"066cdc77-7602-4155-86b5-309283d01644","description":""},{"name":"upload file","id":"626593fe-e206-4180-8d3b-602a0fca3c83","protocolProfileBehavior":{"disableBodyPruning":true},"request":{"auth":{"type":"bearer","bearer":{"basicConfig":[{"key":"token","value":"{{restock_admin_token}}"}]},"isInherited":false},"method":"POST","header":[],"body":{"mode":"formdata","formdata":[{"key":"file","type":"file","src":"/Users/apple/Downloads/17278605601727860560upl66fd0f5043ba7.jpeg"}]},"url":"https://restock-yt1s.onrender.com/api/admin/upload","urlObject":{"protocol":"https","path":["api","admin","upload"],"host":["restock-yt1s","onrender","com"],"query":[],"variable":[]}},"response":[],"_postman_id":"626593fe-e206-4180-8d3b-602a0fca3c83"},{"name":"send-notification","id":"4d89ae19-daaa-4df9-951c-7667e775bc9b","protocolProfileBehavior":{"disableBodyPruning":true},"request":{"auth":{"type":"bearer","bearer":{"basicConfig":[{"key":"token","value":"{{restock_token}}"}]},"isInherited":false},"method":"POST","header":[],"body":{"mode":"raw","raw":"{\n    \"message\": \"Testing push notification from admin\",\n    \"title\": \"push notif test\"\n}","options":{"raw":{"language":"json"}}},"url":"localhost:5002/api/admin/send-notification","urlObject":{"port":"5002","path":["api","admin","send-notification"],"host":["localhost"],"query":[],"variable":[]}},"response":[],"_postman_id":"4d89ae19-daaa-4df9-951c-7667e775bc9b"}],"id":"dc816433-1d91-415e-9203-3e782ebf0400","_postman_id":"dc816433-1d91-415e-9203-3e782ebf0400","description":""},{"name":"user","item":[{"name":"product","item":[{"name":"get product by market id","id":"cfa7e948-e1e9-42de-a738-2a06a62993c5","protocolProfileBehavior":{"disableBodyPruning":true},"request":{"auth":{"type":"bearer","bearer":{"basicConfig":[{"key":"token","value":"{{restock_token}}"}]},"isInherited":false},"method":"GET","header":[],"url":"localhost:5002/api/user/product/market/:marketId","urlObject":{"port":"5002","path":["api","user","product","market",":marketId"],"host":["localhost"],"query":[],"variable":[{"type":"any","value":"d445fc51-e129-454f-a0d0-5dadb22a8bac","key":"marketId"}]}},"response":[],"_postman_id":"cfa7e948-e1e9-42de-a738-2a06a62993c5"},{"name":"get all packages","id":"c050ac30-cb3e-4805-84f3-d12a3db426dd","protocolProfileBehavior":{"disableBodyPruning":true},"request":{"auth":{"type":"bearer","bearer":{"basicConfig":[{"key":"token","value":"{{restock_token}}"}]},"isInherited":false},"method":"GET","header":[],"url":"localhost:6005/api/user/product/packages","urlObject":{"port":"6005","path":["api","user","product","packages"],"host":["localhost"],"query":[],"variable":[]}},"response":[],"_postman_id":"c050ac30-cb3e-4805-84f3-d12a3db426dd"},{"name":"get product by category id","id":"cf3ef7ae-1a22-4051-adf0-083bc91a3b89","protocolProfileBehavior":{"disableBodyPruning":true},"request":{"auth":{"type":"bearer","bearer":{"basicConfig":[{"key":"token","value":"{{restock_token}}"}]},"isInherited":false},"method":"GET","header":[],"url":"localhost:5002/api/user/product/category/:categoryId","urlObject":{"port":"5002","path":["api","user","product","category",":categoryId"],"host":["localhost"],"query":[],"variable":[{"type":"any","value":"4b34a675-0f2f-4ab0-ada7-90eeb4e4ce24","key":"categoryId"}]}},"response":[],"_postman_id":"cf3ef7ae-1a22-4051-adf0-083bc91a3b89"},{"name":"get product by tags","id":"7bc40028-7f8f-4787-8381-bae46abd656b","protocolProfileBehavior":{"disableBodyPruning":true},"request":{"auth":{"type":"bearer","bearer":{"basicConfig":[{"key":"token","value":"{{restock_token}}"}]},"isInherited":false},"method":"GET","header":[],"url":"localhost:5002/api/user/product/tag","urlObject":{"port":"5002","path":["api","user","product","tag"],"host":["localhost"],"query":[],"variable":[]}},"response":[{"id":"ab53e168-8da3-414c-ba76-afa3d0a0542f","name":"get product by tags","originalRequest":{"method":"GET","header":[],"url":"localhost:5002/api/user/product/tag"},"status":"OK","code":200,"_postman_previewlanguage":"json","header":[{"key":"X-Powered-By","value":"Express"},{"key":"Access-Control-Allow-Origin","value":"*"},{"key":"Content-Type","value":"application/json; charset=utf-8"},{"key":"Content-Length","value":"1360"},{"key":"ETag","value":"W/\"550-2s46WknodTg7lHP4JYrSPiO3wk4\""},{"key":"Date","value":"Sun, 16 Feb 2025 18:26:17 GMT"},{"key":"Connection","value":"keep-alive"},{"key":"Keep-Alive","value":"timeout=5"}],"cookie":[],"responseTime":null,"body":"{\n    \"message\": \"product fetched\",\n    \"status\": true,\n    \"data\": [\n        {\n            \"id\": \"6411c7f6-2fb9-48e3-997b-4a079478786d\",\n            \"name\": \"Best deals\",\n            \"description\": \"The all time best deals\",\n            \"type\": \"Products\",\n            \"status\": true,\n            \"createdAt\": \"2025-02-16T14:57:10.561Z\",\n            \"updatedAt\": \"2025-02-16T14:57:10.561Z\",\n            \"taggedProducts\": [\n                {\n                    \"id\": \"27f6a0bb-834a-43d8-b311-363ebe479815\",\n                    \"tagId\": \"6411c7f6-2fb9-48e3-997b-4a079478786d\",\n                    \"marketId\": \"d445fc51-e129-454f-a0d0-5dadb22a8bac\",\n                    \"commodityId\": \"980e58b1-4ae6-49df-a668-49dbbc307d77\",\n                    \"createdAt\": \"2025-02-16T15:03:05.329Z\",\n                    \"updatedAt\": \"2025-02-16T15:03:05.329Z\",\n                    \"commodity\": {\n                        \"id\": \"980e58b1-4ae6-49df-a668-49dbbc307d77\",\n                        \"name\": \"Tomatoes\",\n                        \"price\": 0,\n                        \"status\": true,\n                        \"imageUrl\": \"https://images-prod.healthline.com/hlcmsresource/images/AN_images/tomatoes-1296x728-feature.jpg\",\n                        \"categoryId\": \"4b34a675-0f2f-4ab0-ada7-90eeb4e4ce24\",\n                        \"measurements\": null,\n                        \"createdAt\": \"2025-02-16T12:25:07.336Z\",\n                        \"updatedAt\": \"2025-02-16T12:25:07.336Z\"\n                    },\n                    \"market\": {\n                        \"id\": \"d445fc51-e129-454f-a0d0-5dadb22a8bac\",\n                        \"name\": \"Sabo\",\n                        \"address\": \"359 Herbert Macaulay Wy, Yaba, Lagos 101245, Lagos\",\n                        \"latitude\": 6.45407,\n                        \"longitude\": 3.39467,\n                        \"status\": true,\n                        \"agentId\": \"a3f1af3f-a27b-4661-baab-55775ceb5c1c\",\n                        \"marketImage\": \"https://encrypted-tbn0.gstatic.com/images?q=tbn:ANd9GcQH8ejYsGzDFWdVGAwzTRPYYijifRWhCVN7EQ&s\",\n                        \"createdAt\": \"2025-02-16T12:36:32.298Z\",\n                        \"updatedAt\": \"2025-02-16T12:36:32.298Z\"\n                    }\n                }\n            ],\n            \"taggedMarkets\": []\n        }\n    ]\n}"}],"_postman_id":"7bc40028-7f8f-4787-8381-bae46abd656b"},{"name":"get products","id":"28175ca9-ce5b-421c-ab58-745112c187cf","protocolProfileBehavior":{"disableBodyPruning":true},"request":{"auth":{"type":"bearer","bearer":{"basicConfig":[{"key":"token","value":"{{restock_token}}"}]},"isInherited":false},"method":"GET","header":[],"url":"localhost:5002/api/user/product","urlObject":{"port":"5002","path":["api","user","product"],"host":["localhost"],"query":[],"variable":[]}},"response":[],"_postman_id":"28175ca9-ce5b-421c-ab58-745112c187cf"},{"name":"get products by tag id","id":"dd0d97b4-3b5e-44bd-ba3f-9f86f2cc74e7","protocolProfileBehavior":{"disableBodyPruning":true},"request":{"auth":{"type":"bearer","bearer":{"basicConfig":[{"key":"token","value":"{{restock_token}}"}]},"isInherited":false},"method":"GET","header":[],"url":"localhost:5002/api/user/product/tag/:id","urlObject":{"port":"5002","path":["api","user","product","tag",":id"],"host":["localhost"],"query":[],"variable":[{"type":"any","value":"6411c7f6-2fb9-48e3-997b-4a079478786d","key":"id"}]}},"response":[],"_postman_id":"dd0d97b4-3b5e-44bd-ba3f-9f86f2cc74e7"},{"name":"get single product","id":"4823469b-abf9-4d41-82df-82b7e3e2e3b3","protocolProfileBehavior":{"disableBodyPruning":true},"request":{"auth":{"type":"bearer","bearer":{"basicConfig":[{"key":"token","value":"{{restock_token}}"}]},"isInherited":false},"method":"GET","header":[],"url":"localhost:5002/api/user/product/:marketId/:commodityId","urlObject":{"port":"5002","path":["api","user","product",":marketId",":commodityId"],"host":["localhost"],"query":[],"variable":[{"type":"any","value":"d63baab7-965a-4587-8133-494352bb532a","key":"marketId"},{"type":"any","value":"99f2ccb1-7804-4c05-8cc3-7a90514e238f","key":"commodityId"}]}},"response":[],"_postman_id":"4823469b-abf9-4d41-82df-82b7e3e2e3b3"}],"id":"ec16a101-6ee4-4f39-9918-079fe4c4b427","_postman_id":"ec16a101-6ee4-4f39-9918-079fe4c4b427","description":""},{"name":"account","item":[{"name":"get user address","id":"84eaf147-67c4-4dde-babe-9f417fb49995","protocolProfileBehavior":{"disableBodyPruning":true},"request":{"auth":{"type":"bearer","bearer":{"basicConfig":[{"key":"token","value":"{{restock_token}}"}]},"isInherited":false},"method":"GET","header":[],"url":"localhost:5002/api/user/account/address","urlObject":{"port":"5002","path":["api","user","account","address"],"host":["localhost"],"query":[],"variable":[]}},"response":[],"_postman_id":"84eaf147-67c4-4dde-babe-9f417fb49995"},{"name":"get total referrer","id":"0e48f23a-f407-41f2-916b-961da865fce4","protocolProfileBehavior":{"disableBodyPruning":true},"request":{"auth":{"type":"bearer","bearer":{"basicConfig":[{"key":"token","value":"{{restock_token}}"}]},"isInherited":false},"method":"GET","header":[],"url":"localhost:5002/api/user/account/total-referrer","urlObject":{"port":"5002","path":["api","user","account","total-referrer"],"host":["localhost"],"query":[],"variable":[]}},"response":[],"_postman_id":"0e48f23a-f407-41f2-916b-961da865fce4"},{"name":"get user data","id":"9736da20-0e25-4f0d-9905-09000cc313f6","protocolProfileBehavior":{"disableBodyPruning":true},"request":{"auth":{"type":"bearer","bearer":{"basicConfig":[{"key":"token","value":"{{restock_token}}"}]},"isInherited":false},"method":"GET","header":[],"url":"localhost:5002/api/user/account","urlObject":{"port":"5002","path":["api","user","account"],"host":["localhost"],"query":[],"variable":[]}},"response":[],"_postman_id":"9736da20-0e25-4f0d-9905-09000cc313f6"},{"name":"delete user address","id":"3effdd35-731f-4b35-9874-187eec2f6908","protocolProfileBehavior":{"disableBodyPruning":true},"request":{"auth":{"type":"bearer","bearer":{"basicConfig":[{"key":"token","value":"{{restock_token}}"}]},"isInherited":false},"method":"DELETE","header":[],"url":"localhost:5002/api/user/account/address/:id","urlObject":{"port":"5002","path":["api","user","account","address",":id"],"host":["localhost"],"query":[],"variable":[{"type":"any","value":"","key":"id"}]}},"response":[],"_postman_id":"3effdd35-731f-4b35-9874-187eec2f6908"},{"name":"delete user account","id":"620638d4-0a8e-487a-a6da-b6d267d61fbe","protocolProfileBehavior":{"disableBodyPruning":true},"request":{"auth":{"type":"bearer","bearer":{"basicConfig":[{"key":"token","value":"{{restock_token}}"}]},"isInherited":false},"method":"DELETE","header":[],"body":{"mode":"raw","raw":"{\n    \"password\": \"\",\n    \"reason\": \"\"\n}","options":{"raw":{"language":"json"}}},"url":"localhost:5002/api/user/account","urlObject":{"port":"5002","path":["api","user","account"],"host":["localhost"],"query":[],"variable":[]}},"response":[],"_postman_id":"620638d4-0a8e-487a-a6da-b6d267d61fbe"},{"name":"change default address","id":"fb8a1ec8-52e8-4a72-9ef2-ffeed5839ad8","protocolProfileBehavior":{"disableBodyPruning":true},"request":{"auth":{"type":"bearer","bearer":{"basicConfig":[{"key":"token","value":"{{restock_token}}"}]},"isInherited":false},"method":"PATCH","header":[],"url":"localhost:5002/api/user/account/address/change-default/:id","urlObject":{"port":"5002","path":["api","user","account","address","change-default",":id"],"host":["localhost"],"query":[],"variable":[{"type":"any","value":"b071e275-7838-45a5-a32e-db32ee14639a","key":"id"}]}},"response":[],"_postman_id":"fb8a1ec8-52e8-4a72-9ef2-ffeed5839ad8"},{"name":"create address","id":"bda813b3-ef71-4c5f-b600-9958e11accbb","protocolProfileBehavior":{"disableBodyPruning":true},"request":{"auth":{"type":"bearer","bearer":{"basicConfig":[{"key":"token","value":"{{restock_token}}"}]},"isInherited":false},"method":"POST","header":[],"body":{"mode":"raw","raw":"{\n    \"country\": \"Nigeria\",\n    \"address\": \"4 Islamic St, Ojodu, Ojodu Berger 102109, Ogun State\",\n    \"city\": \"Berger\",\n    \"state\": \"Ogun\",\n    \"houseNumber\": 4,\n    \"landmark\": \"Kosoko road\",\n    \"longitude\": \"\",\n    \"latitude\": \"\"\n}","options":{"raw":{"language":"json"}}},"url":"localhost:5002/api/user/account/address","urlObject":{"port":"5002","path":["api","user","account","address"],"host":["localhost"],"query":[],"variable":[]}},"response":[],"_postman_id":"bda813b3-ef71-4c5f-b600-9958e11accbb"},{"name":"update user data","id":"69a2e4bd-f0fa-40ab-b8dc-338016d18440","protocolProfileBehavior":{"disableBodyPruning":true},"request":{"auth":{"type":"bearer","bearer":{"basicConfig":[{"key":"token","value":"{{restock_token}}"}]},"isInherited":false},"method":"PUT","header":[],"body":{"mode":"raw","raw":"{\n    \"firstName\": \"Adesewa\",\n    \"lastName\": \"Abdullah\",\n    \"gender\": \"Male\", // Female, Male\n    \"phone\": \"08012345678\"\n}","options":{"raw":{"language":"json"}}},"url":"localhost:5002/api/user/account","urlObject":{"port":"5002","path":["api","user","account"],"host":["localhost"],"query":[],"variable":[]}},"response":[],"_postman_id":"69a2e4bd-f0fa-40ab-b8dc-338016d18440"},{"name":"change password","id":"0ee411c3-f57a-4855-ad2b-99eb80692f2f","protocolProfileBehavior":{"disableBodyPruning":true},"request":{"auth":{"type":"bearer","bearer":{"basicConfig":[{"key":"token","value":"{{restock_token}}"}]},"isInherited":false},"method":"PATCH","header":[],"body":{"mode":"raw","raw":"{\n    \"oldPassword\": \"Password@123\"\n}","options":{"raw":{"language":"json"}}},"url":"localhost:5002/api/user/account/change-password","urlObject":{"port":"5002","path":["api","user","account","change-password"],"host":["localhost"],"query":[],"variable":[]}},"response":[],"_postman_id":"0ee411c3-f57a-4855-ad2b-99eb80692f2f"},{"name":"reset password","id":"f9d34851-65b8-4d08-b25f-3efe64a8beca","protocolProfileBehavior":{"disableBodyPruning":true},"request":{"auth":{"type":"bearer","bearer":{"basicConfig":[{"key":"token","value":"{{restock_token}}"}]},"isInherited":false},"method":"PATCH","header":[],"body":{"mode":"raw","raw":"{\n    \"oldPassword\": \"Password@123\",\n    \"newPassword\": \"Password123\",\n    \"otp\": \"718022\"\n}","options":{"raw":{"language":"json"}}},"url":"localhost:5002/api/user/account/reset-password","urlObject":{"port":"5002","path":["api","user","account","reset-password"],"host":["localhost"],"query":[],"variable":[]}},"response":[],"_postman_id":"f9d34851-65b8-4d08-b25f-3efe64a8beca"},{"name":"update profile picture","id":"8f2eaf92-e21e-47a2-9682-86542cb4e9de","protocolProfileBehavior":{"disableBodyPruning":true},"request":{"auth":{"type":"bearer","bearer":{"basicConfig":[{"key":"token","value":"{{restock_token}}"}]},"isInherited":false},"method":"PATCH","header":[],"body":{"mode":"raw","raw":"{\n    \"imageUrl\": \"Password@123\"\n}","options":{"raw":{"language":"json"}}},"url":"localhost:5002/api/user/account/profile-picture","urlObject":{"port":"5002","path":["api","user","account","profile-picture"],"host":["localhost"],"query":[],"variable":[]}},"response":[],"_postman_id":"8f2eaf92-e21e-47a2-9682-86542cb4e9de"}],"id":"c6df6878-ac70-4c27-bc75-fb41e9181c8f","_postman_id":"c6df6878-ac70-4c27-bc75-fb41e9181c8f","description":""},{"name":"order","item":[{"name":"get user order","id":"ea1d09e3-4ba9-4cce-80a8-7f4905f6abed","protocolProfileBehavior":{"disableBodyPruning":true},"request":{"auth":{"type":"bearer","bearer":{"basicConfig":[{"key":"token","value":"{{restock_token}}"}]},"isInherited":false},"method":"GET","header":[],"url":"localhost:5006/api/user/order","urlObject":{"port":"5006","path":["api","user","order"],"host":["localhost"],"query":[],"variable":[]}},"response":[],"_postman_id":"ea1d09e3-4ba9-4cce-80a8-7f4905f6abed"},{"name":"get valid coupons","id":"3b4fa207-8387-4fe4-9f0a-2fbb038f1910","protocolProfileBehavior":{"disableBodyPruning":true},"request":{"auth":{"type":"bearer","bearer":{"basicConfig":[{"key":"token","value":"{{restock_token}}"}]},"isInherited":false},"method":"GET","header":[],"url":"localhost:5006/api/user/order/coupons","urlObject":{"port":"5006","path":["api","user","order","coupons"],"host":["localhost"],"query":[],"variable":[]}},"response":[],"_postman_id":"3b4fa207-8387-4fe4-9f0a-2fbb038f1910"},{"name":"get activated referral bonus list","id":"e6997bb0-c3ef-4878-8156-8771cf05672a","protocolProfileBehavior":{"disableBodyPruning":true},"request":{"auth":{"type":"bearer","bearer":{"basicConfig":[{"key":"token","value":"{{restock_token}}"}]},"isInherited":false},"method":"GET","header":[],"url":"localhost:5006/api/user/order/referral-bonus","urlObject":{"port":"5006","path":["api","user","order","referral-bonus"],"host":["localhost"],"query":[],"variable":[]}},"response":[],"_postman_id":"e6997bb0-c3ef-4878-8156-8771cf05672a"},{"name":"validate coupon","id":"7f9dc523-1a29-4f5d-ab48-a12433c7c501","protocolProfileBehavior":{"disableBodyPruning":true},"request":{"auth":{"type":"bearer","bearer":{"basicConfig":[{"key":"token","value":"{{restock_token}}"}]},"isInherited":false},"method":"POST","header":[],"body":{"mode":"raw","raw":"{\n    \"couponCode\": \"PROMO\",\n    \"total\": 20000\n}","options":{"raw":{"language":"json"}}},"url":"localhost:5006/api/user/order/validate-coupon","urlObject":{"port":"5006","path":["api","user","order","validate-coupon"],"host":["localhost"],"query":[],"variable":[]}},"response":[],"_postman_id":"7f9dc523-1a29-4f5d-ab48-a12433c7c501"},{"name":"initiate payment","id":"9f8de282-f94a-450f-8ef8-039034f94acd","protocolProfileBehavior":{"disableBodyPruning":true},"request":{"auth":{"type":"bearer","bearer":{"basicConfig":[{"key":"token","value":"{{restock_token}}"}]},"isInherited":false},"method":"POST","header":[],"body":{"mode":"raw","raw":"{\n  \"price\": 22886.03,\n  \"deliveryId\": \"8ad163d2-9089-4cd4-a2b2-79ee9375b4d2\",\n  \"marketId\": \"d63baab7-965a-4587-8133-494352bb532a\",\n  \"items\": [\n    {\"id\": \"980e58b1-4ae6-49df-a668-49dbbc307d77\", \"measurementId\": \"f6089056-c176-49c1-9a32-c51a8ec3f248\", \"quantity\": 1}\n  ]\n//   \"couponCode\": \"\" // optional\n\n}","options":{"raw":{"language":"json"}}},"url":"localhost:6005/api/user/order/initialize-payment/:type","urlObject":{"port":"6005","path":["api","user","order","initialize-payment",":type"],"host":["localhost"],"query":[],"variable":[{"type":"any","value":"Monnify","key":"type"}]}},"response":[],"_postman_id":"9f8de282-f94a-450f-8ef8-039034f94acd"},{"name":"initiate payment with safehaven","id":"f793d02a-8722-4454-9952-44a2e5a28e62","protocolProfileBehavior":{"disableBodyPruning":true},"request":{"auth":{"type":"bearer","bearer":{"basicConfig":[{"key":"token","value":"{{restock_token}}"}]},"isInherited":false},"method":"POST","header":[],"body":{"mode":"raw","raw":"{\n    \"amount\": 30000,\n    \"email\": \"habeehola18@gmail.com\",\n    \"fullname\": \"Rasheed dada\",\n    \"deliveryFee\": 1500,\n    \"serviceCharge\": 1000\n}","options":{"raw":{"language":"json"}}},"url":"localhost:6005/api/user/order/initialize-payment-safehaven","urlObject":{"port":"6005","path":["api","user","order","initialize-payment-safehaven"],"host":["localhost"],"query":[],"variable":[]}},"response":[],"_postman_id":"f793d02a-8722-4454-9952-44a2e5a28e62"},{"name":"generate payment link","id":"c5c8f364-a53a-4fee-af78-524018fce207","protocolProfileBehavior":{"disableBodyPruning":true},"request":{"auth":{"type":"bearer","bearer":{"basicConfig":[{"key":"token","value":"{{restock_token}}"}]},"isInherited":false},"method":"GET","header":[],"body":{"mode":"raw","raw":"","options":{"raw":{"language":"json"}}},"url":"localhost:5002/api/user/order/generate-payment-link/:orderId","urlObject":{"port":"5002","path":["api","user","order","generate-payment-link",":orderId"],"host":["localhost"],"query":[],"variable":[{"type":"any","value":"","key":"orderId"}]}},"response":[],"_postman_id":"c5c8f364-a53a-4fee-af78-524018fce207"},{"name":"cancel order","id":"fca2720b-b19e-4fd8-8d25-a7ceed8938cf","protocolProfileBehavior":{"disableBodyPruning":true},"request":{"auth":{"type":"bearer","bearer":{"basicConfig":[{"key":"token","value":"{{restock_token}}"}]},"isInherited":false},"method":"PUT","header":[],"body":{"mode":"raw","raw":"","options":{"raw":{"language":"json"}}},"url":"localhost:5002/api/user/order/cancel-order/:orderId","urlObject":{"port":"5002","path":["api","user","order","cancel-order",":orderId"],"host":["localhost"],"query":[],"variable":[{"type":"any","value":"","key":"orderId"}]}},"response":[],"_postman_id":"fca2720b-b19e-4fd8-8d25-a7ceed8938cf"},{"name":"verify payment","id":"ddf4bd8d-20a9-46ff-85d3-85f4bfdd5c9c","protocolProfileBehavior":{"disableBodyPruning":true},"request":{"auth":{"type":"bearer","bearer":{"basicConfig":[{"key":"token","value":"{{restock_token}}"}]},"isInherited":false},"method":"PUT","header":[],"body":{"mode":"raw","raw":"","options":{"raw":{"language":"json"}}},"url":"localhost:5002/api/user/order/verify-payment/:reference","urlObject":{"port":"5002","path":["api","user","order","verify-payment",":reference"],"host":["localhost"],"query":[],"variable":[{"type":"any","value":"","key":"reference"}]}},"response":[],"_postman_id":"ddf4bd8d-20a9-46ff-85d3-85f4bfdd5c9c"}],"id":"cfc41003-b01a-4d33-aaac-f12323c6a676","_postman_id":"cfc41003-b01a-4d33-aaac-f12323c6a676","description":""},{"name":"market","item":[{"name":"get markets according user location","id":"f62c8402-4292-47f5-827f-2faf82571e91","protocolProfileBehavior":{"disableBodyPruning":true},"request":{"auth":{"type":"bearer","bearer":{"basicConfig":[{"key":"token","value":"{{restock_token}}"}]},"isInherited":false},"method":"GET","header":[],"url":"localhost:5002/api/user/market","urlObject":{"port":"5002","path":["api","user","market"],"host":["localhost"],"query":[],"variable":[]}},"response":[],"_postman_id":"f62c8402-4292-47f5-827f-2faf82571e91"}],"id":"abeca11f-d1b9-4f9f-9df3-186bc0f5fc01","_postman_id":"abeca11f-d1b9-4f9f-9df3-186bc0f5fc01","description":""},{"name":"category","item":[{"name":"get all category","id":"5ce25003-5c87-4f5f-8072-c7e743a343f5","protocolProfileBehavior":{"disableBodyPruning":true},"request":{"auth":{"type":"bearer","bearer":{"basicConfig":[{"key":"token","value":"{{restock_token}}"}]},"isInherited":false},"method":"GET","header":[],"url":"localhost:5002/api/user/category","urlObject":{"port":"5002","path":["api","user","category"],"host":["localhost"],"query":[],"variable":[]}},"response":[],"_postman_id":"5ce25003-5c87-4f5f-8072-c7e743a343f5"}],"id":"af2ee2d2-c8c8-441d-9b38-5fe02e03102a","_postman_id":"af2ee2d2-c8c8-441d-9b38-5fe02e03102a","description":""},{"name":"banner","item":[{"name":"get all banner","id":"b894e96c-456c-42cc-9a7f-c5a5b792791a","protocolProfileBehavior":{"disableBodyPruning":true},"request":{"auth":{"type":"bearer","bearer":{"basicConfig":[{"key":"token","value":"{{restock_token}}"}]},"isInherited":false},"method":"GET","header":[],"url":"localhost:5002/api/user/banner","urlObject":{"port":"5002","path":["api","user","banner"],"host":["localhost"],"query":[],"variable":[]}},"response":[],"_postman_id":"b894e96c-456c-42cc-9a7f-c5a5b792791a"}],"id":"924cf46d-65bb-462b-8c7e-6f045c172026","_postman_id":"924cf46d-65bb-462b-8c7e-6f045c172026","description":""},{"name":"settings","item":[{"name":"get settings config","id":"1f97abb8-5b93-452e-a2eb-c4f907aa9a6b","protocolProfileBehavior":{"disableBodyPruning":true},"request":{"auth":{"type":"bearer","bearer":{"basicConfig":[{"key":"token","value":"<token>"}]},"isInherited":false},"method":"POST","header":[],"body":{"mode":"raw","raw":"{\n    \"deliveryId\": \"8ad163d2-9089-4cd4-a2b2-79ee9375b4d2\",\n    \"marketId\": \"d63baab7-965a-4587-8133-494352bb532a\"\n}","options":{"raw":{"language":"json"}}},"url":"localhost:5002/api/user/setting","urlObject":{"port":"5002","path":["api","user","setting"],"host":["localhost"],"query":[],"variable":[]}},"response":[{"id":"ea1ba126-9b03-475b-87fe-baa6b883e272","name":"config","originalRequest":{"method":"GET","header":[],"url":"localhost:5002/api/user/setting"},"status":"OK","code":200,"_postman_previewlanguage":"json","header":[{"key":"X-Powered-By","value":"Express"},{"key":"Access-Control-Allow-Origin","value":"*"},{"key":"Content-Type","value":"application/json; charset=utf-8"},{"key":"Content-Length","value":"38"},{"key":"ETag","value":"W/\"26-TzcP1/JGdLKzdoWwglRABq0TdXA\""},{"key":"Date","value":"Sun, 02 Mar 2025 13:53:44 GMT"},{"key":"Connection","value":"keep-alive"},{"key":"Keep-Alive","value":"timeout=5"}],"cookie":[],"responseTime":null,"body":"{\n    \"serviceCharge\": 10,\n    \"capPrice\": 200000\n}"}],"_postman_id":"1f97abb8-5b93-452e-a2eb-c4f907aa9a6b"},{"name":"get delivery charge","id":"e1503167-3277-4267-89bc-706a80c43917","protocolProfileBehavior":{"disableBodyPruning":true},"request":{"auth":{"type":"bearer","bearer":{"basicConfig":[{"key":"token","value":"{{restock_token}}"}]},"isInherited":false},"method":"GET","header":[],"url":"localhost:5002/api/user/setting/delivery-charge","urlObject":{"port":"5002","path":["api","user","setting","delivery-charge"],"host":["localhost"],"query":[],"variable":[]}},"response":[{"id":"2a0f2212-1a5a-4f29-803a-8c38b1216633","name":"delivery charge","originalRequest":{"method":"GET","header":[],"url":"localhost:5002/api/user/setting/delivery-charge"},"status":"OK","code":200,"_postman_previewlanguage":"json","header":[{"key":"X-Powered-By","value":"Express"},{"key":"Access-Control-Allow-Origin","value":"*"},{"key":"Content-Type","value":"application/json; charset=utf-8"},{"key":"Content-Length","value":"47"},{"key":"ETag","value":"W/\"2f-Ve9Sso/HJsAdjJkZnyFDUDHBzgo\""},{"key":"Date","value":"Sun, 02 Mar 2025 13:54:15 GMT"},{"key":"Connection","value":"keep-alive"},{"key":"Keep-Alive","value":"timeout=5"}],"cookie":[],"responseTime":null,"body":"{\n    \"address\": \"\",\n    \"distance\": \"10km\",\n    \"price\": 200000\n}"}],"_postman_id":"e1503167-3277-4267-89bc-706a80c43917"}],"id":"96fc5b59-a9e3-4832-abd7-d4414bd51736","_postman_id":"96fc5b59-a9e3-4832-abd7-d4414bd51736","description":""},{"name":"shopper","item":[{"name":"get shoppers","id":"c4db7da6-17ad-4f07-ab66-c4f8f23574ed","protocolProfileBehavior":{"disableBodyPruning":true},"request":{"auth":{"type":"bearer","bearer":{"basicConfig":[{"key":"token","value":"{{restock_token}}"}]},"isInherited":false},"method":"GET","header":[],"url":"localhost:5002/api/user/shopper?marketId","urlObject":{"port":"5002","path":["api","user","shopper"],"host":["localhost"],"query":[{"key":"marketId","value":null}],"variable":[]}},"response":[],"_postman_id":"c4db7da6-17ad-4f07-ab66-c4f8f23574ed"}],"id":"1228b27a-fa03-4a8c-b42b-3bc962a009d3","_postman_id":"1228b27a-fa03-4a8c-b42b-3bc962a009d3","description":""},{"name":"export file","id":"2f8cb2c2-08f3-4c0a-af13-65f931b3aeec","protocolProfileBehavior":{"disableBodyPruning":true},"request":{"auth":{"type":"noauth","isInherited":false},"method":"GET","header":[],"body":{"mode":"formdata","formdata":[]},"url":"localhost:5007/api/export","urlObject":{"port":"5007","path":["api","export"],"host":["localhost"],"query":[],"variable":[]}},"response":[],"_postman_id":"2f8cb2c2-08f3-4c0a-af13-65f931b3aeec"},{"name":"upload file","id":"4d22c99f-1557-43a2-b2a8-e78c6fe8c728","protocolProfileBehavior":{"disableBodyPruning":true},"request":{"auth":{"type":"bearer","bearer":{"basicConfig":[{"key":"token","value":"{{restock_token}}"}]},"isInherited":false},"method":"POST","header":[],"body":{"mode":"formdata","formdata":[{"key":"file","type":"file","src":"/Users/apple/Downloads/image-1.jpg"}]},"url":"localhost:5002/api/user/updload","urlObject":{"port":"5002","path":["api","user","updload"],"host":["localhost"],"query":[],"variable":[]}},"response":[],"_postman_id":"4d22c99f-1557-43a2-b2a8-e78c6fe8c728"},{"name":"create waitlist","id":"92d92650-e939-46b9-9a17-61e564923aa0","protocolProfileBehavior":{"disableBodyPruning":true},"request":{"auth":{"type":"noauth","isInherited":false},"method":"POST","header":[],"body":{"mode":"raw","raw":"{\n    \"fullName\": \"\",\n    \"note\": \"\",\n    \"email\": \"\",\n    \"phone\": \"\",\n    \"gender\": \"\"\n}","options":{"raw":{"language":"json"}}},"url":"localhost:5002/api/auth/waitlist","urlObject":{"port":"5002","path":["api","auth","waitlist"],"host":["localhost"],"query":[],"variable":[]}},"response":[],"_postman_id":"92d92650-e939-46b9-9a17-61e564923aa0"},{"name":"get home stats","id":"ca1be3a2-87ec-45fa-9f56-1f57f23d8fee","protocolProfileBehavior":{"disableBodyPruning":true},"request":{"auth":{"type":"noauth","isInherited":false},"method":"GET","header":[],"body":{"mode":"raw","raw":"{\n    \"fullName\": \"\",\n    \"note\": \"\",\n    \"email\": \"\",\n    \"phone\": \"\",\n    \"gender\": \"\"\n}","options":{"raw":{"language":"json"}}},"url":"localhost:5002/api/auth/home-stat","urlObject":{"port":"5002","path":["api","auth","home-stat"],"host":["localhost"],"query":[],"variable":[]}},"response":[],"_postman_id":"ca1be3a2-87ec-45fa-9f56-1f57f23d8fee"}],"id":"9c925400-8658-47fe-a077-28bbed49e82f","_postman_id":"9c925400-8658-47fe-a077-28bbed49e82f","description":""},{"name":"public","item":[{"name":"categories","id":"bdd99fdd-1844-4bab-9e1d-d1a3f615df39","protocolProfileBehavior":{"disableBodyPruning":true},"request":{"method":"GET","header":[],"url":"localhost:6005/api/public/categories","urlObject":{"port":"6005","path":["api","public","categories"],"host":["localhost"],"query":[],"variable":[]}},"response":[],"_postman_id":"bdd99fdd-1844-4bab-9e1d-d1a3f615df39"},{"name":"packages","id":"e6e22c0f-5f8b-4207-ab13-b86cb3d1ee2d","protocolProfileBehavior":{"disableBodyPruning":true},"request":{"method":"GET","header":[],"url":"localhost:6005/api/public/packages","urlObject":{"port":"6005","path":["api","public","packages"],"host":["localhost"],"query":[],"variable":[]}},"response":[],"_postman_id":"e6e22c0f-5f8b-4207-ab13-b86cb3d1ee2d"},{"name":"markets","id":"4a1608bd-f8aa-4dbc-970e-a109c364676c","protocolProfileBehavior":{"disableBodyPruning":true},"request":{"method":"GET","header":[],"url":"localhost:6005/api/public/markets","urlObject":{"port":"6005","path":["api","public","markets"],"host":["localhost"],"query":[],"variable":[]}},"response":[],"_postman_id":"4a1608bd-f8aa-4dbc-970e-a109c364676c"},{"name":"product by id","id":"7ed244bb-4a8b-42d0-94ef-72df4f2174b4","protocolProfileBehavior":{"disableBodyPruning":true},"request":{"method":"GET","header":[],"url":"localhost:6005/api/public/product/:marketId/:commodityId","urlObject":{"port":"6005","path":["api","public","product",":marketId",":commodityId"],"host":["localhost"],"query":[],"variable":[{"type":"any","value":"","key":"marketId"},{"type":"any","value":"","key":"commodityId"}]}},"response":[],"_postman_id":"7ed244bb-4a8b-42d0-94ef-72df4f2174b4"},{"name":"products by market id","id":"9930880d-d3f5-4e6f-ba57-ab1293634fcb","protocolProfileBehavior":{"disableBodyPruning":true},"request":{"method":"GET","header":[],"url":"localhost:6005/api/public/market/products/d63baab7-965a-4587-8133-494352bb532a","urlObject":{"port":"6005","path":["api","public","market","products","d63baab7-965a-4587-8133-494352bb532a"],"host":["localhost"],"query":[],"variable":[]}},"response":[],"_postman_id":"9930880d-d3f5-4e6f-ba57-ab1293634fcb"}],"id":"bb2ba3ba-c0c5-4aad-a115-ac52449e9a6b","_postman_id":"bb2ba3ba-c0c5-4aad-a115-ac52449e9a6b","description":""}]}